payabli/__init__.py
payabli/bill/__init__.py
payabli/bill/client.py
payabli/bill/raw_client.py
payabli/bill/types/__init__.py
payabli/bill/types/bill_out_data.py
payabli/bill/types/bill_out_data_scheduled_options.py
payabli/bill/types/bill_response.py
payabli/bill/types/bill_response_data.py
payabli/bill/types/edit_bill_response.py
payabli/bill/types/get_bill_response.py
payabli/bill/types/modify_approval_bill_response.py
payabli/bill/types/set_approved_bill_response.py
payabli/boarding/__init__.py
payabli/boarding/client.py
payabli/boarding/raw_client.py
payabli/boarding/types/__init__.py
payabli/boarding/types/add_application_request.py
payabli/charge_backs/__init__.py
payabli/charge_backs/client.py
payabli/charge_backs/raw_client.py
payabli/charge_backs/types/__init__.py
payabli/charge_backs/types/add_response_response.py
payabli/charge_backs/types/charge_back_response.py
payabli/charge_backs/types/chargeback_message.py
payabli/charge_backs/types/chargeback_query_records.py
payabli/check_capture/__init__.py
payabli/check_capture/client.py
payabli/check_capture/raw_client.py
payabli/check_capture/types/__init__.py
payabli/check_capture/types/check_capture_request.py
payabli/check_capture/types/check_capture_response.py
payabli/client.py
payabli/cloud/__init__.py
payabli/cloud/client.py
payabli/cloud/raw_client.py
payabli/cloud/types/__init__.py
payabli/cloud/types/add_device_response.py
payabli/cloud/types/remove_device_response.py
payabli/core/__init__.py
payabli/core/api_error.py
payabli/core/client_wrapper.py
payabli/core/datetime_utils.py
payabli/core/file.py
payabli/core/force_multipart.py
payabli/core/http_client.py
payabli/core/http_response.py
payabli/core/http_sse/__init__.py
payabli/core/http_sse/_api.py
payabli/core/http_sse/_decoders.py
payabli/core/http_sse/_exceptions.py
payabli/core/http_sse/_models.py
payabli/core/jsonable_encoder.py
payabli/core/pydantic_utilities.py
payabli/core/query_encoder.py
payabli/core/remove_none_from_dict.py
payabli-0.0.302.dist-info/METADATA
payabli-0.0.302.dist-info/WHEEL
payabli-0.0.302.dist-info/RECORD
